WeixinXiaoChengxukaifaWendang/README.md
WeixinXiaoChengxukaifaWendang/__init__.py
WeixinXiaoChengxukaifaWendang/__main__.py
WeixinXiaoChengxukaifaWendang/file.epub
WeixinXiaoChengxukaifaWendang/index.html
WeixinXiaoChengxukaifaWendang/css/__init__.py
WeixinXiaoChengxukaifaWendang/css/annotations.css
WeixinXiaoChengxukaifaWendang/css/main.css
WeixinXiaoChengxukaifaWendang/css/normalize.css
WeixinXiaoChengxukaifaWendang/css/popup.css
WeixinXiaoChengxukaifaWendang/font/__init__.py
WeixinXiaoChengxukaifaWendang/font/fontello.eot
WeixinXiaoChengxukaifaWendang/font/fontello.svg
WeixinXiaoChengxukaifaWendang/font/fontello.ttf
WeixinXiaoChengxukaifaWendang/font/fontello.woff
WeixinXiaoChengxukaifaWendang/img/__init__.py
WeixinXiaoChengxukaifaWendang/img/annotator-glyph-sprite.png
WeixinXiaoChengxukaifaWendang/img/annotator-icon-sprite.png
WeixinXiaoChengxukaifaWendang/img/apple-touch-icon.png
WeixinXiaoChengxukaifaWendang/img/cancelfullscreen.png
WeixinXiaoChengxukaifaWendang/img/close.png
WeixinXiaoChengxukaifaWendang/img/fullscreen.png
WeixinXiaoChengxukaifaWendang/img/loader.gif
WeixinXiaoChengxukaifaWendang/img/menu-icon.png
WeixinXiaoChengxukaifaWendang/img/save.png
WeixinXiaoChengxukaifaWendang/img/saved.png
WeixinXiaoChengxukaifaWendang/img/settings-s.png
WeixinXiaoChengxukaifaWendang/img/settings.png
WeixinXiaoChengxukaifaWendang/img/star.png
WeixinXiaoChengxukaifaWendang/js/__init__.py
WeixinXiaoChengxukaifaWendang/js/epub.js
WeixinXiaoChengxukaifaWendang/js/epub.min.js
WeixinXiaoChengxukaifaWendang/js/epub.min.map
WeixinXiaoChengxukaifaWendang/js/hooks.min.js
WeixinXiaoChengxukaifaWendang/js/hooks.min.map
WeixinXiaoChengxukaifaWendang/js/reader.js
WeixinXiaoChengxukaifaWendang/js/reader.js.map
WeixinXiaoChengxukaifaWendang/js/reader.min.js
WeixinXiaoChengxukaifaWendang/js/reader.min.map
WeixinXiaoChengxukaifaWendang/js/hooks/__init__.py
WeixinXiaoChengxukaifaWendang/js/hooks/extensions/__init__.py
WeixinXiaoChengxukaifaWendang/js/hooks/extensions/highlight.js
weixin_xiao_chengxukaifa_wendang-2024.3.2.0.dist-info/METADATA
weixin_xiao_chengxukaifa_wendang-2024.3.2.0.dist-info/WHEEL
weixin_xiao_chengxukaifa_wendang-2024.3.2.0.dist-info/entry_points.txt
weixin_xiao_chengxukaifa_wendang-2024.3.2.0.dist-info/top_level.txt
weixin_xiao_chengxukaifa_wendang-2024.3.2.0.dist-info/RECORD
